{"_invocation_id": "209405d2-eb25-4823-84f5-2518fc2dc3ae", "linked": {"0": {"name": "source.aspects.event_sink.user_profile", "type": "source", "succ": [16]}, "1": {"name": "source.aspects.event_sink.external_id", "type": "source", "succ": [16]}, "2": {"name": "source.aspects.event_sink.course_blocks", "type": "source", "succ": [33]}, "3": {"name": "source.aspects.event_sink.course_overviews", "type": "source", "succ": [31]}, "4": {"name": "source.aspects.xapi.xapi_events_all", "type": "source", "succ": [15]}, "5": {"name": "model.aspects.fact_problem_engagement", "type": "model"}, "6": {"name": "model.aspects.fact_problem_responses", "type": "model", "succ": [5, 11]}, "7": {"name": "model.aspects.int_problems_per_subsection", "type": "model", "succ": [5, 14]}, "8": {"name": "model.aspects.dim_user_pii", "type": "model", "succ": [5, 10, 14, 6, 21, 25, 35, 36, 37, 38, 41, 19, 45, 46]}, "9": {"name": "model.aspects.dim_course_blocks", "type": "model", "succ": [7, 12, 6, 20, 25, 23, 34, 35, 36]}, "10": {"name": "model.aspects.fact_learner_problem_summary", "type": "model", "succ": [51, 53, 54]}, "11": {"name": "model.aspects.int_problem_results", "type": "model", "succ": [10, 14, 50]}, "12": {"name": "model.aspects.int_problem_hints", "type": "model", "succ": [10]}, "13": {"name": "model.aspects.problem_events", "type": "model", "succ": [12, 6]}, "14": {"name": "model.aspects.fact_problem_responses_extended", "type": "model"}, "15": {"name": "model.aspects.xapi_events_all_parsed", "type": "model", "succ": [13, 22, 26, 27, 28, 32, 18, 30, 40, 44, 47]}, "16": {"name": "model.aspects.user_pii", "type": "model", "succ": [8]}, "17": {"name": "model.aspects.dim_at_risk_learners", "type": "model"}, "18": {"name": "model.aspects.navigation_events", "type": "model", "succ": [17, 35]}, "19": {"name": "model.aspects.fact_student_status", "type": "model", "succ": [17, 61]}, "20": {"name": "model.aspects.int_videos_per_subsection", "type": "model", "succ": [24]}, "21": {"name": "model.aspects.fact_video_plays", "type": "model", "succ": [24]}, "22": {"name": "model.aspects.video_playback_events", "type": "model", "succ": [21]}, "23": {"name": "model.aspects.dim_course_blocks_extended", "type": "model", "succ": [21]}, "24": {"name": "model.aspects.fact_video_engagement", "type": "model"}, "25": {"name": "model.aspects.fact_transcript_usage", "type": "model"}, "26": {"name": "model.aspects.video_transcript_events", "type": "model", "succ": [25]}, "27": {"name": "model.aspects.fact_instance_actors", "type": "model"}, "28": {"name": "model.aspects.fact_instance_events", "type": "model"}, "29": {"name": "model.aspects.fact_instance_enrollments", "type": "model", "succ": [55]}, "30": {"name": "model.aspects.enrollment_events", "type": "model", "succ": [29, 38, 39]}, "31": {"name": "model.aspects.course_names", "type": "model", "succ": [29, 9, 38, 41, 19, 45, 46]}, "32": {"name": "model.aspects.fact_instance_courses", "type": "model"}, "33": {"name": "model.aspects.course_block_names", "type": "model", "succ": [9, 41, 45]}, "34": {"name": "model.aspects.int_pages_per_subsection", "type": "model", "succ": [37]}, "35": {"name": "model.aspects.fact_navigation", "type": "model", "succ": [36, 37]}, "36": {"name": "model.aspects.fact_navigation_dropoff", "type": "model", "succ": [56]}, "37": {"name": "model.aspects.fact_navigation_completion", "type": "model"}, "38": {"name": "model.aspects.fact_enrollments", "type": "model", "succ": [57]}, "39": {"name": "model.aspects.fact_enrollment_status", "type": "model", "succ": [19, 58]}, "40": {"name": "model.aspects.completion_events", "type": "model", "succ": [41]}, "41": {"name": "model.aspects.fact_completions", "type": "model"}, "42": {"name": "model.aspects.fact_learner_course_status", "type": "model", "succ": [19, 60]}, "43": {"name": "model.aspects.fact_learner_course_grade", "type": "model", "succ": [19]}, "44": {"name": "model.aspects.grading_events", "type": "model", "succ": [42, 45, 43]}, "45": {"name": "model.aspects.fact_grades", "type": "model", "succ": [59]}, "46": {"name": "model.aspects.fact_forum_interactions", "type": "model"}, "47": {"name": "model.aspects.forum_events", "type": "model", "succ": [46]}, "48": {"name": "test.aspects.a_tag", "type": "test"}, "49": {"name": "test.aspects.get_problem_id", "type": "test"}, "50": {"name": "test.aspects.problem_results_uniqueness", "type": "test"}, "51": {"name": "test.aspects.learner_problem_summary_uniqueness", "type": "test"}, "52": {"name": "test.aspects.get_problem_id_with_ccx", "type": "test"}, "53": {"name": "test.aspects.not_null_fact_learner_problem_summary_success.76b52cb2da", "type": "test"}, "54": {"name": "test.aspects.not_null_fact_learner_problem_summary_attempts.817beed32b", "type": "test"}, "55": {"name": "test.aspects.accepted_values_fact_instance_enrollments_enrollment_status__registered__unregistered.305ffdf696", "type": "test"}, "56": {"name": "test.aspects.accepted_values_fact_navigation_dropoff_rollup_name__section__subsection.8afafb193f", "type": "test"}, "57": {"name": "test.aspects.accepted_values_fact_enrollments_enrollment_status__registered__unregistered.f8d10203f4", "type": "test"}, "58": {"name": "test.aspects.accepted_values_fact_enrollment_status_enrollment_status__registered__unregistered.893527c11f", "type": "test"}, "59": {"name": "test.aspects.accepted_values_fact_grades_grade_type__course__subsection__problem.712bd50c2f", "type": "test"}, "60": {"name": "test.aspects.accepted_values_fact_learner_course_status_approving_state__passed__failed.f9c0c1b85f", "type": "test"}, "61": {"name": "test.aspects.accepted_values_fact_student_status_enrollment_status__registered__unregistered.53cae8a0f3", "type": "test"}}}